{
  "sections": {
    "slideshow_gym": {
      "type": "slideshow",
      "blocks": {
        "s1": {
          "type": "_slide",
          "settings": {
            "image": "hero_gym_1.png",
            "heading": "PUSH YOUR LIMITS",
            "subheading": "Premium Performance Gear",
            "button_label": "SHOP NOW"
          }
        }
      },
      "block_order": ["s1"]
    },
    "welcome_message": {
      "type": "custom-liquid",
      "settings": {
        "custom_liquid": "<div style='text-align:center; padding: 80px 20px;'><h2 style='font-size: 40px;'>WELCOME TO ONYX FITNESS</h2><p style='font-size: 18px;'>The Gym Demo is now fully synced. Add your products and images to complete the look!</p></div>"
      }
    },
    "categories_gym": {
      "type": "collection-list",
      "blocks": {
        "c1": {
          "type": "group",
          "settings": {
            "background_image": "category_men.png"
          }
        },
        "c2": {
          "type": "group",
          "settings": {
            "background_image": "category_women.png"
          }
        }
      },
      "block_order": ["c1", "c2"]
    },
    "marquee_gym": {
      "type": "marquee",
      "blocks": {
        "t1": {
          "type": "text",
          "settings": {
            "text": "JOIN THE ELITE FITNESS CLUB • FREE SHIPPING OVER $99"
          }
        }
      },
      "block_order": ["t1"]
    }
  },
  "order": ["slideshow_gym", "welcome_message", "categories_gym", "marquee_gym"]
}